MANIFEST.in
README.md
setup.py
audioowl/__init__.py
audioowl/analyze.py
audioowl.egg-info/PKG-INFO
audioowl.egg-info/SOURCES.txt
audioowl.egg-info/dependency_links.txt
audioowl.egg-info/not-zip-safe
audioowl.egg-info/requires.txt
audioowl.egg-info/top_level.txt