Metadata-Version: 2.1
Name: audioowl
Version: 0.0.13
Summary: Fast and simple music and audio analysis using RNN in Python
Home-page: https://github.com/dodiku/AudioOwl
Author: Dror Ayalon
Author-email: d.stamail@gmail.com
License: MIT
Keywords: Fast and simple music and audio analysis using RNN in Python
Platform: UNKNOWN
Classifier: Development Status :: 4 - Beta
Classifier: License :: OSI Approved :: MIT License
Classifier: Programming Language :: Python :: 3.6
Classifier: Topic :: Multimedia :: Sound/Audio :: Analysis
